peersight/__init__.py
peersight/agent.py
peersight/config.py
peersight/core.py
peersight/llm_client.py
peersight/main.py
peersight/parser.py
peersight/prompts.py
peersight/utils.py
peersight-0.1.1.dist-info/METADATA
peersight-0.1.1.dist-info/WHEEL
peersight-0.1.1.dist-info/entry_points.txt
peersight-0.1.1.dist-info/top_level.txt
peersight-0.1.1.dist-info/RECORD
