Metadata-Version: 2.4
Name: peersight
Version: 0.1.1
Summary: PeerSight: An AI-powered command-line tool for simulating academic paper reviews using local LLMs via Ollama.
Author-email: AbdElKader Seif El Islem RAHMANI <a.e.k426rahmani@gmail.com>
License: MIT
Project-URL: Homepage, https://github.com/RAHAMNIabdelkaderseifelislem/PeerSight
Project-URL: Bug Tracker, https://github.com/RAHAMNIabdelkaderseifelislem/PeerSight/issues
Keywords: ai,llm,ollama,review,academic,nlp,cli
Classifier: Development Status :: 3 - Alpha
Classifier: Intended Audience :: Science/Research
Classifier: Intended Audience :: Developers
Classifier: License :: OSI Approved :: MIT License
Classifier: Programming Language :: Python :: 3
Classifier: Programming Language :: Python :: 3.9
Classifier: Programming Language :: Python :: 3.10
Classifier: Programming Language :: Python :: 3.11
Classifier: Programming Language :: Python :: 3.12
Classifier: Environment :: Console
Classifier: Topic :: Scientific/Engineering
Classifier: Topic :: Text Processing :: Linguistic
Classifier: Operating System :: OS Independent
Requires-Python: >=3.9
Requires-Dist: python-dotenv
Requires-Dist: requests
Requires-Dist: pypdf
Provides-Extra: test
Requires-Dist: pytest; extra == "test"
Requires-Dist: pytest-mock; extra == "test"
Provides-Extra: dev
Requires-Dist: pytest; extra == "dev"
Requires-Dist: pytest-mock; extra == "dev"
Requires-Dist: build; extra == "dev"
Requires-Dist: black; extra == "dev"
Requires-Dist: ruff; extra == "dev"
Requires-Dist: pre-commit; extra == "dev"
Requires-Dist: twine; extra == "dev"
Requires-Dist: pypdf; extra == "dev"
